Metadata-Version: 1.0
Name: collective.recipe.distutils
Version: 0.1
Summary: A buildout recipe to install distutils Python packages.
Home-page: http://svn.plone.org/svn/collective/buildout/collective.recipe.distutils
Author: Kevin Teague
Author-email: kevin@bud.ca
License: GPL
Keywords: build distutils
Platform: UNKNOWN
Classifier: Development Status :: 3 - Alpha
Classifier: Environment :: Plugins
Classifier: Intended Audience :: System Administrators
Classifier: Framework :: Buildout
Classifier: License :: OSI Approved :: GNU General Public License (GPL)
Classifier: Programming Language :: Python
Classifier: Topic :: System :: Installation/Setup
Classifier: Topic :: Software Development :: Libraries :: Python Modules
